Workbook
Name aporte: Simulador!$D$15
Name patrimonio: Simulador!$D$18
Name qtd_anos: Simulador!$D$16
Name rendimento_carteira: Simulador!$D$11
Name salario: Simulador!$D$10
Name sugestao_investimento: Simulador!$D$12
Name taxa_mensal: Simulador!$D$17

Sheet Simulador
B9: CONFIGURAÇÕES
B10: Salário | D10: 2000
B11: Rendimento Carteira | D11: 0.006
B12: Sugestão de Investimento | D12: =$D$10*30% -> 600
B14: INVESTIMENTO MENSAL
B15: Quanto investir por mês? | D15: 200
B16: Por quantos anos? | D16: 5
B17: Taxa de rendimento mensal? | D17: 0.01079
B18: Patrimônio acumulado? | D18: =FV(taxa_mensal,qtd_anos*12,aporte*-1) -> 16755.383
B19: Dividendos mensais? | D19: =patrimonio*rendimento_carteira -> 100.5323
B21: CENÁRIOS
B22: Período (anos) | C22: Patrimônio Acumulado | D22: Dividendos
B23: 2 | C23: =FV(taxa_mensal,$B23*12,aporte*-1) -> 5445.5255 | D23: =C23*rendimento_carteira -> 32.673153
B24: 5 | C24: =FV(taxa_mensal,$B24*12,aporte*-1) -> 16755.383 | D24: =C24*rendimento_carteira -> 100.5323
B25: 10 | C25: =FV(taxa_mensal,$B25*12,aporte*-1) -> 48656.843 | D25: =C25*rendimento_carteira -> 291.94106
B26: 20 | C26: =FV(taxa_mensal,$B26*12,aporte*-1) -> 225039.68 | D26: =C26*rendimento_carteira -> 1350.2381
B27: 30 | C27: =FV(taxa_mensal,$B27*12,aporte*-1) -> 864433.93 | D27: =C27*rendimento_carteira -> 5186.6036
B29: PERFIL | C29: Agressivo
B30: VALOR A SER INVESTIDO POR MÊS | C30: =aporte -> 200
B32: TIPO DE FII | C32: PERCENTUAL SUGERIDO | D32: VALORES
B33: PAPEL | C33: =VLOOKUP($C$29&" - " &B33,tab_Apoios!$A:$D,4,0) -> 0.5 | D33: =C33*$C$30 -> 100
B34: TIJOLO | C34: =VLOOKUP($C$29&" - " &B34,tab_Apoios!$A:$D,4,0) -> 0.1 | D34: =C34*$C$30 -> 20
B35: HÍBRIDO | C35: =VLOOKUP($C$29&" - " &B35,tab_Apoios!$A:$D,4,0) -> 0.05 | D35: =C35*$C$30 -> 10
B36: FOFs | C36: =VLOOKUP($C$29&" - " &B36,tab_Apoios!$A:$D,4,0) -> 0.05 | D36: =C36*$C$30 -> 10
B37: DESENVOLVIMENTO | C37: =VLOOKUP($C$29&" - " &B37,tab_Apoios!$A:$D,4,0) -> 0.2 | D37: =C37*$C$30 -> 40
B38: HOTELARIAS | C38: =VLOOKUP($C$29&" - " &B38,tab_Apoios!$A:$D,4,0) -> 0.1 | D38: =C38*$C$30 -> 20
D39: =SUM(D33:D38) -> 200

Sheet tab_Apoios
A2: CHAVE | B2: PERFIL | C2: TIPO DE FII | D2: %
A3: =B3&" - "&C3 -> CONSERVADOR - PAPEL | B3: CONSERVADOR | C3: PAPEL | D3: 0.3
A4: =B4&" - "&C4 -> CONSERVADOR - TIJOLO | B4: CONSERVADOR | C4: TIJOLO | D4: 0.5
A5: =B5&" - "&C5 -> CONSERVADOR - HÍBRIDO | B5: CONSERVADOR | C5: HÍBRIDO | D5: 0.1
A6: =B6&" - "&C6 -> CONSERVADOR - FOFs | B6: CONSERVADOR | C6: FOFs | D6: 0.1
A7: =B7&" - "&C7 -> CONSERVADOR - DESENVOLVIMENTO | B7: CONSERVADOR | C7: DESENVOLVIMENTO | D7: 0
A8: =B8&" - "&C8 -> CONSERVADOR - HOTELARIAS | B8: CONSERVADOR | C8: HOTELARIAS | D8: 0
A9: =B9&" - "&C9 -> MODERADO - PAPEL | B9: MODERADO | C9: PAPEL | D9: 0.32
A10: =B10&" - "&C10 -> MODERADO - TIJOLO | B10: MODERADO | C10: TIJOLO | D10: 0.35
A11: =B11&" - "&C11 -> MODERADO - HÍBRIDO | B11: MODERADO | C11: HÍBRIDO | D11: 0.08
A12: =B12&" - "&C12 -> MODERADO - FOFs | B12: MODERADO | C12: FOFs | D12: 0.05
A13: =B13&" - "&C13 -> MODERADO - DESENVOLVIMENTO | B13: MODERADO | C13: DESENVOLVIMENTO | D13: 0.1
A14: =B14&" - "&C14 -> MODERADO - HOTELARIAS | B14: MODERADO | C14: HOTELARIAS | D14: 0.1
... A20: =B20&" - "&C20 -> AGRESSIVO - HOTELARIAS | B20: AGRESSIVO | C20: HOTELARIAS | D20: 0.1
